cdepy/__init__.py
cdepy/cdeairflowpython.py
cdepy/cdeconnection.py
cdepy/cdecredentials.py
cdepy/cdejob.py
cdepy/cdemanager.py
cdepy/cderepositories.py
cdepy/cderesource.py
cdepy/utils.py
cdepy-0.1.20.dist-info/LICENSE
cdepy-0.1.20.dist-info/METADATA
cdepy-0.1.20.dist-info/WHEEL
cdepy-0.1.20.dist-info/top_level.txt
cdepy-0.1.20.dist-info/RECORD
