Metadata-Version: 2.1
Name: cdepy
Version: 0.1.20
Summary: A Python Package for interacting with Cloudera Data Engineering Clusters
Home-page: https://github.com/pdefusco/cdepy
Author: Paul de Fusco
License: MIT
Classifier: Development Status :: 4 - Beta
Classifier: Intended Audience :: Developers
Classifier: Topic :: Software Development :: Build Tools
Classifier: License :: OSI Approved :: MIT License
Classifier: Programming Language :: Python :: 3
Requires-Python: >=2.7
License-File: LICENSE
Requires-Dist: pyparsing ==3.0.9
Requires-Dist: requests-toolbelt ==1.0.0
Requires-Dist: xmltodict ==0.13.0
